<?xml version="1.0" encoding="UTF-8"?>
<con:soapui-project id="a62737e8-ca7d-4d7d-ae30-becfd8b9eb1d" created="3.53.0" activeEnvironment="Default environment" encryptionMode="Not encrypted" name="Activity4" resourceRoot="" projectVersion="" updated="3.53.0 2024-05-13T12:06:25Z" xmlns:con="http://eviware.com/soapui/config"><con:settings/><con:interface xsi:type="con:RestService" id="8055d8be-b3ff-442e-9d0d-8c8194a66d00" wadlVersion="http://wadl.dev.java.net/2009/02" name="http://ipwhois.app" type="rest" xmlns:xsi="http://www.w3.org/2001/XMLSchema-instance"><con:settings id="dae635d3-1075-4770-bdb2-84194d66f24f"/><con:definitionCache type="TEXT" rootPart=""/><con:endpoints><con:endpoint>http://ipwhois.app</con:endpoint></con:endpoints><con:resource name="IP" path="/json/{IP}" id="5c2595e0-d9fb-4296-97c2-922440e366c7"><con:settings/><con:parameters/><con:method name="IP" id="ba938100-b06f-4ebe-be21-1ee217fd7cd4" method="GET"><con:settings/><con:parameters><con:parameter required="true"><con:name>IP</con:name><con:value>IP</con:value><con:style>TEMPLATE</con:style><con:default>IP</con:default><con:path xsi:nil="true"/><con:description xsi:nil="true"/></con:parameter></con:parameters><con:representation type="RESPONSE"><con:mediaType>application/json; charset=utf-8</con:mediaType><con:status>200</con:status><con:params/><con:element xmlns:ns="http://ipwhois.app/json/66.12.25.226">ns:Response</con:element></con:representation><con:request name="Request 1" id="92d1f605-0bb0-45d3-a477-45b1731e724b" mediaType="application/json"><con:settings/><con:endpoint>http://ipwhois.app</con:endpoint><con:parameters><con:entry key="IP" value="IP"/></con:parameters><con:parameterOrder><con:entry>IP</con:entry></con:parameterOrder></con:request></con:method></con:resource></con:interface><con:testSuite id="3f749996-2e30-4c4b-aaf1-a8e7e2f1dfad" name="http://ipwhois.app Test Suite"><con:settings id="0efd4acf-e42b-44ec-bef9-a01fd3661b2d"/><con:runType>SEQUENTIAL</con:runType><con:testCase id="ff2343d7-e76e-4547-9729-26ef79b40520" discardOkResults="false" failOnError="true" failTestCaseOnErrors="true" keepSession="false" name="http://ipwhois.app Test Case 1" searchProperties="true" timeout="0"><con:settings/><con:testStep type="datasource" name="Data Source" id="f62ccc96-f538-4c1b-afc2-64950f06a375"><con:settings/><con:config xsi:type="con:DataSourceStep" xmlns:xsi="http://www.w3.org/2001/XMLSchema-instance"><con:dataSource type="File"><con:configuration><fileName>C:/Users/SauravBharti/Desktop/Alchemy/25APRIL M1/IPList.txt</fileName><separator>,</separator><trim>true</trim><charset>Cp1252</charset><quotedValues>false</quotedValues></con:configuration></con:dataSource><con:shared>true</con:shared><con:restartShared>true</con:restartShared><con:property>IP</con:property><con:restartOnRun>true</con:restartOnRun><con:stopDatasourceExhausted>false</con:stopDatasourceExhausted></con:config></con:testStep><con:testStep type="restrequest" name="GetIP" id="e2dad45a-dda8-468c-884b-1839d7d20e26"><con:settings/><con:config service="http://ipwhois.app" resourcePath="/json/{IP}" methodName="IP" xsi:type="con:RestRequestStep" xmlns:xsi="http://www.w3.org/2001/XMLSchema-instance"><con:restRequest name="GetIP" id="92d1f605-0bb0-45d3-a477-45b1731e724b" mediaType="application/json"><con:settings><con:setting id="com.eviware.soapui.impl.wsdl.WsdlRequest@request-headers">&lt;xml-fragment/></con:setting></con:settings><con:endpoint>http://ipwhois.app</con:endpoint><con:request/><con:originalUri>http://ipwhois.app/json/66.12.25.226</con:originalUri><con:assertion type="JsonPath Existence Match" id="1b763e95-061f-4da6-a070-f2acaeb5c2f9" name="JSONPath Existence Match"><con:configuration><path>$['country']</path><content>true</content><allowWildcards>false</allowWildcards><ignoreNamspaceDifferences>false</ignoreNamspaceDifferences><ignoreComments>false</ignoreComments></con:configuration></con:assertion><con:credentials><con:selectedAuthProfile>No Authorization</con:selectedAuthProfile><con:authType>No Authorization</con:authType></con:credentials><con:jmsConfig JMSDeliveryMode="PERSISTENT"/><con:parameters><con:entry key="IP" value="${Data Source#IP}"/></con:parameters><con:parameterOrder><con:entry>IP</con:entry></con:parameterOrder></con:restRequest></con:config></con:testStep><con:testStep type="datasourceloop" name="Data Source Loop" id="b1d92843-5b06-47f3-9bd3-7986289255d7"><con:settings/><con:config><dataSourceStep>Data Source</dataSourceStep><targetStep>GetIP</targetStep><discardResults>true</discardResults></con:config></con:testStep><con:properties/><con:reportParameters/></con:testCase><con:properties/><con:reportParameters/></con:testSuite><con:requirements/><con:properties/><con:wssContainer/><con:databaseConnectionContainer/><con:jmsConnectionContainer/><con:oAuth2ProfileContainer/><con:oAuth1ProfileContainer/><con:reporting><con:xmlTemplates/><con:parameters/></con:reporting><con:eventHandlers type="RequestFilter.filterRequest" name="RequestFilter.filterRequest"><con:script>// Sample event script to add custom HTTP header to all outgoing REST, SOAP and HTTP(S) calls
// This code is often used for adding custom authentication to ReadyAPI functional tests

// If hardcoding the token, uncomment and change line 5
// token = '4567'

// If your token is parameterized in Project level custom property, uncomment line 8
// token = request.parent.testCase.testSuite.project.getProperty('auth_token').getValue()

// To modify all outgoing calls, remove comments from lines 11 to 16
// headers = request.requestHeaders
// if (headers.containsKey('auth_token2') == false) {
//   headers.put('auth_token2', token)
//   request.requestHeaders = headers
// }</con:script></con:eventHandlers><con:eventHandlers type="TestRunListener.afterStep" name="TestRunListener.afterStep"><con:script>// Save all test step results into files
// Change the directory path in line 5 to a location where you want to store details
// then uncomment lines 5 to 10

// filePath = 'C:\\tempOutputDirectory\\'
// fos = new java.io.FileOutputStream(filePath + testStepResult.testStep.label + '.txt', true)
// pw = new java.io.PrintWriter(fos)
// testStepResult.writeTo(pw)
// pw.close()
// fos.close()</con:script></con:eventHandlers><con:authRepository/><con:tags/></con:soapui-project>